dotenv_manager/__init__.py
dotenv_manager/logger.py
dotenv_manager/manager_decorator.py
dotenv_manager/singleton.py
dotenv_manager-0.1.1.dist-info/METADATA
dotenv_manager-0.1.1.dist-info/WHEEL
dotenv_manager-0.1.1.dist-info/RECORD
