Metadata-Version: 2.1
Name: dotenv-manager
Version: 0.1.1
Summary: 
Home-page: https://github.com/teodorToshkov/dotenv-manager
Author: Teodor Toshkov
Author-email: teodor.toshkov95@gmail.com
Requires-Python: >=3.10,<4.0
Classifier: Programming Language :: Python :: 3
Classifier: Programming Language :: Python :: 3.10
Classifier: Programming Language :: Python :: 3.11
Requires-Dist: python-dotenv (>=1.0.0,<2.0.0)
Project-URL: Repository, https://github.com/teodorToshkov/dotenv-manager
